ptftpd-1.2.dist-info/DESCRIPTION.rst
ptftpd-1.2.dist-info/METADATA
ptftpd-1.2.dist-info/RECORD
ptftpd-1.2.dist-info/WHEEL
ptftpd-1.2.dist-info/entry_points.txt
ptftpd-1.2.dist-info/metadata.json
ptftpd-1.2.dist-info/pbr.json
ptftpd-1.2.dist-info/top_level.txt
ptftpd-1.2.dist-info/zip-safe
ptftplib/__init__.py
ptftplib/bootpserver.py
ptftplib/dhcpserver.py
ptftplib/notify.py
ptftplib/proto.py
ptftplib/pxeserver.py
ptftplib/state.py
ptftplib/tftpclient.py
ptftplib/tftpserver.py
ptftplib/version.py
