Metadata-Version: 2.0
Name: ptftpd
Version: 1.2
Summary: pTFTPd, a pure-Python TFTP tool suite that works
Home-page: https://github.com/mpetazzoni/ptftpd
Author: Maxime Petazzoni
Author-email: maxime.petazzoni@bulix.org
License: GNU General Public License v2
Platform: UNKNOWN
Classifier: Operating System :: OS Independent
Classifier: Programming Language :: Python
Requires-Dist: netifaces
